zfitpy/__init__.py
zfitpy/engformatter.py
zfitpy/impedancedata.py
zfitpy/model.py
zfitpy/models.py
zfitpy/plotter.py
zfitpy/zfit.py
zfitpy/zfitter.py
zfitpy/zfitterbase.py
zfitpy/zfitterbrute.py
zfitpy/zfittercurve.py
zfitpy/scripts/__init__.py
zfitpy/scripts/zfitpy.py
zfitpy-0.6.1.dist-info/METADATA
zfitpy-0.6.1.dist-info/WHEEL
zfitpy-0.6.1.dist-info/entry_points.txt
zfitpy-0.6.1.dist-info/top_level.txt
zfitpy-0.6.1.dist-info/RECORD
