Metadata-Version: 2.1
Name: zfitpy
Version: 0.6.1
Summary: Electrical model fitting to impedance data
Home-page: https://github.com/mph-/zfitpy
Author: Michael Hayes
Author-email: michael.hayes@canterbury.ac.nz
License: UNKNOWN
Download-URL: https://github.com/mph-/zfitpy
Platform: UNKNOWN
Classifier: Programming Language :: Python :: 3
Classifier: License :: OSI Approved :: GNU Lesser General Public License v2 or later (LGPLv2+)
Classifier: Operating System :: OS Independent
Requires-Python: >=3.6
Requires-Dist: lcapy
Requires-Dist: matplotlib
Requires-Dist: numpy
Requires-Dist: scipy
Requires-Dist: setuptools
Provides-Extra: doc
Requires-Dist: ipython ; extra == 'doc'
Requires-Dist: sphinx ; extra == 'doc'
Provides-Extra: release
Requires-Dist: twine ; extra == 'release'
Requires-Dist: wheel ; extra == 'release'
Provides-Extra: test
Requires-Dist: flake8 ; extra == 'test'
Requires-Dist: flake8-bugbear ; extra == 'test'
Requires-Dist: flake8-comprehensions ; extra == 'test'
Requires-Dist: flake8-requirements ; extra == 'test'
Requires-Dist: nose ; extra == 'test'
